ansible_vault/__init__.py
ansible_vault/__main__.py
ansible_vault/ciphers.py
ansible_vault/cli.py
ansible_vault/constants.py
ansible_vault/exceptions.py
ansible_vault/secrets.py
ansible_vault/utils.py
ansible_vault/vault.py
ansible_vault_win-1.0.0.dist-info/LICENSE.txt
ansible_vault_win-1.0.0.dist-info/METADATA
ansible_vault_win-1.0.0.dist-info/WHEEL
ansible_vault_win-1.0.0.dist-info/entry_points.txt
ansible_vault_win-1.0.0.dist-info/top_level.txt
ansible_vault_win-1.0.0.dist-info/RECORD
