Metadata-Version: 2.1
Name: ansible-vault-win
Version: 1.0.0
Summary: Stand-alone Ansible Vault CLI that works on Windows
Home-page: https://github.com/sparkyb/ansible-vault-win
Author: Ben Buchwald
Author-email: ben@ngcreative.com
License: MIT
Platform: UNKNOWN
Classifier: Development Status :: 5 - Production/Stable
Classifier: Environment :: Console
Classifier: Intended Audience :: Developers
Classifier: Intended Audience :: Information Technology
Classifier: Intended Audience :: System Administrators
Classifier: License :: OSI Approved :: MIT License
Classifier: Natural Language :: English
Classifier: Operating System :: OS Independent
Classifier: Programming Language :: Python :: 3.6
Classifier: Programming Language :: Python :: 3.7
Classifier: Programming Language :: Python :: 3.8
Classifier: Topic :: System :: Installation/Setup
Classifier: Topic :: System :: Systems Administration
Classifier: Topic :: Utilities
Requires-Python: >=3.6
Requires-Dist: cryptography
